README.rst
setup.py
changetip/__init__.py
changetip.egg-info/PKG-INFO
changetip.egg-info/SOURCES.txt
changetip.egg-info/dependency_links.txt
changetip.egg-info/requires.txt
changetip.egg-info/top_level.txt
changetip/bots/__init__.py
changetip/bots/base.py