Metadata-Version: 1.1
Name: changetip
Version: 0.3.3
Summary: ChangeTip helper library
Home-page: https://github.com/changecoin/changetip-python
Author: ChangeCoin, Inc.
Author-email: oss@changecoin.com
License: MIT
Keywords: changetip,changecoin,bitcoin,tipping,micropayments
Platform: UNKNOWN
Classifier: Development Status :: 2 - Pre-Alpha
Classifier: License :: OSI Approved :: MIT License
Classifier: Programming Language :: Python
Classifier: Intended Audience :: Developers
